dsl/__init__.py
dsl/blowfish.py
dsl/codify.py
dsl/dashi.py
dsl/dinj.py
dsl/express.py
dsl/lexc.py
dsl/mixes.py
dsl/orm.py
dsl/processes.py
dsl/tasks.py
dsl/api/__init__.py
dsl/api/instance.py
dsl/api/endpoints/__init__.py
dsl/api/endpoints/users.py
dsl/server/__init__.py
dsl/server/instance.py
dsl/server/endpoints/__init__.py
dsl/server/endpoints/users.py
dsl/sql/__init__.py
tdsl/__init__.py
tdsl/auth.py
tdsl/blowfish.py
tdsl/codify.py
tdsl/dashi.py
tdsl/dinj.py
tdsl/express.py
tdsl/lexc.py
tdsl/main.py
tdsl/mixes.py
tdsl/orm.py
tdsl/processes.py
tdsl/render.py
tdsl/tasks.py
tdsl/xsqlalchemy.py
tdsl/pyramid_jwt/__init__.py
tdsl/pyramid_jwt/policy.py
tdsl/server/__init__.py
tdsl/server/adminviews.py
tdsl/server/api.py
tdsl/server/dbinstall.py
tdsl/server/devdb.py
tdsl/server/instance.py
tdsl/server/notify.py
tdsl/server/sotscap.py
tdsl/server/defaults/__init__.py
tdsl/server/defaults/templates/__init__.py
tdsl/sql/__init__.py
tdsl/tests/__init__.py
tdsl/tests/conversions.py
tdsl/tests/create_application_rec_test.py
tdsl/tests/domain_refl_test.py
tdsl/tests/domain_test.py
tdsl/tests/emulation.py
tdsl/tests/formatting_tmp.py
tdsl/tests/ftp.py
tdsl/tests/metaclasses.py
tdsl/tests/metacoding.py
tdsl/tests/partitioning.py
tdsl/tests/partitiontable.py
tdsl/tests/popentest.py
tdsl/tests/runtimetest.py
tdsl/tests/soql.py
tdsl/tests/speech.py
tdsl/tests/speechtotext.py
tdsl/tests/sqlalchemy_init.py
tdsl/tests/test_dateshift.py
tdsl/tests/test_dinj_config.py
tdsl/tests/test_multiprocessing.py
tdsl/tests/test_notify.py
tdsl/tests/test_passlib.py
tdsl/tests/test_process.py
tdsl/tests/test_redis_hm.py
tdsl/tests/test_round.py
tdsl/tests/test_switch.py
tdsl/tests/test_zmq_client.py
tdsl/tests/test_zmq_server.py
tdsl/tests/tsv_trunc.py
tdsl/tests/types.py
tdsl/tests/unittests.py
tdsl/tests/xcsv.py
tdsl/tests/xexcel.py
truvioncore-1.0.0.dist-info/METADATA
truvioncore-1.0.0.dist-info/WHEEL
truvioncore-1.0.0.dist-info/top_level.txt
truvioncore-1.0.0.dist-info/RECORD
