Metadata-Version: 2.1
Name: truvioncore
Version: 1.0.0
Summary: Truvion Core Classes and DSL
Author: Mat Mathews Brown
Author-email: mbrown@truvion.com
Classifier: Programming Language :: Python :: 3.10
Requires-Dist: arrow (==1.2.3)
Requires-Dist: async-timeout (==4.0.2)
Requires-Dist: attrs (==22.1.0)
Requires-Dist: certifi (==2022.9.24)
Requires-Dist: charset-normalizer (==2.1.1)
Requires-Dist: exceptiongroup (==1.0.4)
Requires-Dist: hupper (==1.10.3)
Requires-Dist: idna (==3.4)
Requires-Dist: iniconfig (==1.1.1)
Requires-Dist: isodate (==0.6.1)
Requires-Dist: Mako (==1.2.4)
Requires-Dist: MarkupSafe (==2.1.1)
Requires-Dist: numpy (==1.23.5)
Requires-Dist: packaging (==21.3)
Requires-Dist: pandas (==1.5.2)
Requires-Dist: passlib (==1.7.4)
Requires-Dist: PasteDeploy (==3.0.1)
Requires-Dist: plaster (==1.1.2)
Requires-Dist: plaster-pastedeploy (==1.0.1)
Requires-Dist: pluggy (==1.0.0)
Requires-Dist: psutil (==5.9.4)
Requires-Dist: pycrypto (==2.6.1)
Requires-Dist: PyJWT (==2.6.0)
Requires-Dist: pyparsing (==3.0.9)
Requires-Dist: pyramid (==2.0)
Requires-Dist: pyramid-mako (==1.1.0)
Requires-Dist: pytest (==7.2.0)
Requires-Dist: python-dateutil (==2.8.2)
Requires-Dist: pytz (==2022.6)
Requires-Dist: PyYAML (==6.0)
Requires-Dist: pyzmq (==24.0.1)
Requires-Dist: redis (==4.3.5)
Requires-Dist: requests (==2.28.1)
Requires-Dist: scipy (==1.9.3)
Requires-Dist: six (==1.16.0)
Requires-Dist: SQLAlchemy (==1.4.44)
Requires-Dist: sqlparse (==0.4.3)
Requires-Dist: toml (==0.10.2)
Requires-Dist: tomli (==2.0.1)
Requires-Dist: translationstring (==1.4)
Requires-Dist: urllib3 (==1.26.13)
Requires-Dist: uWSGI (==2.0.21)
Requires-Dist: venusian (==3.0.0)
Requires-Dist: WebOb (==1.8.7)
Requires-Dist: zmq (==0.0.0)
Requires-Dist: zope.deprecation (==4.4.0)
Requires-Dist: zope.interface (==5.5.2)
